README.txt
setup.py
socksproxy/__init__.py
socksproxy/async_socks.py
socksproxy/blocking_socks.py
socksproxy/main.py
socksproxy/protocol.py
socksproxy/ssh.py
socksproxy.egg-info/PKG-INFO
socksproxy.egg-info/SOURCES.txt
socksproxy.egg-info/dependency_links.txt
socksproxy.egg-info/entry_points.txt
socksproxy.egg-info/requires.txt
socksproxy.egg-info/top_level.txt
test/test_server.py