Metadata-Version: 1.0
Name: socksproxy
Version: 0.1
Summary: SOCKS4/5 proxy with SSH support.
Home-page: http://bitbucket.org/dcs/socksproxy/
Author: Dave St.Germain
Author-email: dave@st.germa.in
License: UNKNOWN
Platform: UNKNOWN
Classifier: Development Status :: 3 - Alpha
Classifier: Environment :: Console
Classifier: Intended Audience :: End Users/Desktop
Classifier: License :: OSI Approved :: BSD License
Classifier: Operating System :: POSIX
Classifier: Programming Language :: Python :: 2
Classifier: Topic :: Internet :: Proxy Servers
